pairfinder/SETTINGS.py
pairfinder/__init__.py
pairfinder/utils.py
pairfinder/builds/__init__.py
pairfinder/builds/asset.py
pairfinder/builds/pairplotlib.py
pairfinder/builds/statistics.py
pairfinder/builds/xlsx_manager.py
pairfinder/data/__init__.py
pairfinder/data/db.py
pairfinder/data/naver.py
pairfinder/data/source.py
pairfinder/data/yahoo.py
pairfinder/models/__init__.py
pairfinder/models/peer_analysis.py
pairfinder/models/spread_builder.py
pairfinder-1.0.4.dist-info/METADATA
pairfinder-1.0.4.dist-info/WHEEL
pairfinder-1.0.4.dist-info/top_level.txt
pairfinder-1.0.4.dist-info/RECORD
