Metadata-Version: 2.1
Name: pairfinder
Version: 1.0.4
Summary: Finder for pairs trading
Home-page: https://github.com/parallel/pairfinder
Author: parallel
Author-email: parallel9973@gmail.com
License: MIT
Platform: UNKNOWN
Classifier: Programming Language :: Python :: 3
Classifier: License :: OSI Approved :: MIT License
Classifier: Operating System :: OS Independent
